ro_lib/__init__.py
ro_lib/_http_client.py
ro_lib/_types.py
ro_lib/_utils.py
ro_lib/api.py
ro_lib/errors.py
ro_lib/endpoints/base.py
ro_lib/endpoints/get_user_info.py
ro_lib-1.1.0.dist-info/METADATA
ro_lib-1.1.0.dist-info/WHEEL
ro_lib-1.1.0.dist-info/licenses/LICENSE
ro_lib-1.1.0.dist-info/RECORD
