Metadata-Version: 2.4
Name: ro-lib
Version: 1.1.0
Summary: private roblox library
Project-URL: Homepage, https://github.com/vangauthic/ro-lib/
Author-email: Andrew Petty <andrewtpetty03@gmail.com>
License: MIT
License-File: LICENSE
Requires-Python: >=3.7
Requires-Dist: aiohttp>=3.8.0
Provides-Extra: test
Requires-Dist: pytest-asyncio>=0.20.0; extra == 'test'
Requires-Dist: pytest>=7.0.0; extra == 'test'
